Metadata-Version: 2.1
Name: seoapi
Version: 2020.6.2
Summary: Библиотека для сервиса seoapi.ru
Home-page: https://github.com/pavelmaksimov/seoapi-lib
Author: Pavel Maksimov
License: MIT
Keywords: python,seo,api,seoapi
Platform: UNKNOWN
Classifier: Programming Language :: Python :: 3
Classifier: License :: OSI Approved :: MIT License
Requires-Python: >=3.6
